[{"type":"constructor","inputs":[{"name":"_preconfServiceManager","type":"address","internalType":"contract IServiceManager"}],"stateMutability":"nonpayable"},{"type":"function","name":"addValidators","inputs":[{"name":"pubkeys","type":"tuple[]","internalType":"struct BLS12381.G1Point[]","components":[{"name":"x","type":"uint256[2]","internalType":"uint256[2]"},{"name":"y","type":"uint256[2]","internalType":"uint256[2]"}]},{"name":"signatures","type":"tuple[]","internalType":"struct BLS12381.G2Point[]","components":[{"name":"x","type":"uint256[2]","internalType":"uint256[2]"},{"name":"x_I","type":"uint256[2]","internalType":"uint256[2]"},{"name":"y","type":"uint256[2]","internalType":"uint256[2]"},{"name":"y_I","type":"uint256[2]","internalType":"uint256[2]"}]}],"outputs":[],"stateMutability":"nonpayable"},{"type":"function","name":"deregisterPreconfer","inputs":[{"name":"lastIndexWitness","type":"address","internalType":"address"}],"outputs":[],"stateMutability":"nonpayable"},{"type":"function","name":"preconferToIndex","inputs":[{"name":"","type":"address","internalType":"address"}],"outputs":[{"name":"","type":"uint256","internalType":"uint256"}],"stateMutability":"view"},{"type":"function","name":"preconferToNonce","inputs":[{"name":"","type":"address","internalType":"address"}],"outputs":[{"name":"","type":"uint256","internalType":"uint256"}],"stateMutability":"view"},{"type":"function","name":"preconferToPubKeyHashToTimestamp","inputs":[{"name":"","type":"address","internalType":"address"},{"name":"","type":"bytes32","internalType":"bytes32"}],"outputs":[{"name":"","type":"uint256","internalType":"uint256"}],"stateMutability":"view"},{"type":"function","name":"registerPreconfer","inputs":[{"name":"operatorSignature","type":"tuple","internalType":"struct ISignatureUtils.SignatureWithSaltAndExpiry","components":[{"name":"signature","type":"bytes","internalType":"bytes"},{"name":"salt","type":"bytes32","internalType":"bytes32"},{"name":"expiry","type":"uint256","internalType":"uint256"}]}],"outputs":[],"stateMutability":"nonpayable"},{"type":"function","name":"removeValidators","inputs":[{"name":"validatorPubKeyHashes","type":"bytes32[]","internalType":"bytes32[]"}],"outputs":[],"stateMutability":"nonpayable"},{"type":"event","name":"PreconferDeregistered","inputs":[{"name":"preconfer","type":"address","indexed":true,"internalType":"address"}],"anonymous":false},{"type":"event","name":"PreconferRegistered","inputs":[{"name":"preconfer","type":"address","indexed":true,"internalType":"address"},{"name":"index","type":"uint256","indexed":true,"internalType":"uint256"}],"anonymous":false},{"type":"event","name":"ValidatorAdded","inputs":[{"name":"preconfer","type":"address","indexed":true,"internalType":"address"},{"name":"compressedPubKey","type":"uint256[2]","indexed":false,"internalType":"uint256[2]"}],"anonymous":false},{"type":"event","name":"ValidatorRemoved","inputs":[{"name":"preconfer","type":"address","indexed":true,"internalType":"address"},{"name":"validatorPubKeyHash","type":"bytes32","indexed":false,"internalType":"bytes32"}],"anonymous":false},{"type":"error","name":"ArrayLengthMismatch","inputs":[]},{"type":"error","name":"InvalidValidatorPubKeyHash","inputs":[]},{"type":"error","name":"InvalidValidatorSignature","inputs":[]},{"type":"error","name":"LastIndexWitnessIncorrect","inputs":[]},{"type":"error","name":"PreconferAlreadyRegistered","inputs":[]},{"type":"error","name":"PreconferNotRegistered","inputs":[]}]